superlimo/__init__.py
superlimo/base_model.py
superlimo/derive_drift.py
superlimo/lib.py
superlimo/matcher.py
superlimo/superlimo.py
superlimo/superpoint_open.py
superlimo/weights.pth
superlimo-0.1.1.dist-info/LICENSE
superlimo-0.1.1.dist-info/METADATA
superlimo-0.1.1.dist-info/WHEEL
superlimo-0.1.1.dist-info/entry_points.txt
superlimo-0.1.1.dist-info/top_level.txt
superlimo-0.1.1.dist-info/RECORD
