Metadata-Version: 2.1
Name: superlimo
Version: 0.1.1
Summary: SuperPoint-based Lagrangian Ice MOtion algorithm
Author: Sean Chua
Author-email: "Anton A. Korosov" <anton.korosov@nersc.no>
License:                                  Apache License
Project-URL: Repository, https://github.com/nansencenter/py-thesaurus-interface
Keywords: sea ice drift,SAR,computer vision,machine learning
Classifier: Development Status :: 3 - Alpha
Classifier: Environment :: Plugins
Classifier: Environment :: Console
Classifier: Intended Audience :: Information Technology
Classifier: Intended Audience :: Science/Research
Classifier: License :: OSI Approved :: Apache Software License
Classifier: Natural Language :: English
Classifier: Operating System :: OS Independent
Classifier: Programming Language :: Python
Classifier: Topic :: Scientific/Engineering
Classifier: Topic :: Scientific/Engineering :: Image Processing
Classifier: Topic :: Scientific/Engineering :: Oceanography
Classifier: Topic :: Utilities
Classifier: Topic :: Software Development :: Libraries :: Python Modules
License-File: LICENSE
Requires-Dist: numpy
Requires-Dist: matplotlib
Requires-Dist: pyproj
Requires-Dist: scipy
Requires-Dist: torch
Requires-Dist: nansat
Requires-Dist: omegaconf
Requires-Dist: scikit-image
